<annotation>
	<folder>train2014</folder>
	<filename>000778.jpg</filename>
	<path>F:\&#22788;&#29702;&#30149;&#23475;&#25968;&#25454;&#38598;\images\train2014\IMG_4292.jpg</path>
	<source>
		<database>Unknown</database>
	</source>
	<size>
		<width>4032</width>
		<height>3024</height>
		<depth>3</depth>
	</size>
	<segmented>0</segmented>
	<object>
		<name>healthy</name>
		<pose>Unspecified</pose>
		<truncated>0</truncated>
		<difficult>0</difficult>
		<bndbox>
			<xmin>209</xmin>
			<ymin>1856</ymin>
			<xmax>812</xmax>
			<ymax>2762</ymax>
		</bndbox>
	</object>
	<object>
		<name>healthy</name>
		<pose>Unspecified</pose>
		<truncated>0</truncated>
		<difficult>0</difficult>
		<bndbox>
			<xmin>700</xmin>
			<ymin>1394</ymin>
			<xmax>1547</xmax>
			<ymax>2584</ymax>
		</bndbox>
	</object>
	<object>
		<name>healthy</name>
		<pose>Unspecified</pose>
		<truncated>0</truncated>
		<difficult>0</difficult>
		<bndbox>
			<xmin>1669</xmin>
			<ymin>1434</ymin>
			<xmax>3478</xmax>
			<ymax>2240</ymax>
		</bndbox>
	</object>
	<object>
		<name>healthy</name>
		<pose>Unspecified</pose>
		<truncated>0</truncated>
		<difficult>0</difficult>
		<bndbox>
			<xmin>2144</xmin>
			<ymin>531</ymin>
			<xmax>3469</xmax>
			<ymax>1269</ymax>
		</bndbox>
	</object>
	<object>
		<name>healthy</name>
		<pose>Unspecified</pose>
		<truncated>0</truncated>
		<difficult>0</difficult>
		<bndbox>
			<xmin>3</xmin>
			<ymin>6</ymin>
			<xmax>1684</xmax>
			<ymax>1656</ymax>
		</bndbox>
	</object>
</annotation>