<annotation>
	<folder>train2014</folder>
	<filename>DSC05115.jpg</filename>
	<path>F:\&#22788;&#29702;&#30149;&#23475;&#25968;&#25454;&#38598;\images\train2014\DSC05115.jpg</path>
	<source>
		<database>Unknown</database>
	</source>
	<size>
		<width>2736</width>
		<height>1824</height>
		<depth>3</depth>
	</size>
	<segmented>0</segmented>
	<object>
		<name>chihuo_low</name>
		<pose>Unspecified</pose>
		<truncated>0</truncated>
		<difficult>0</difficult>
		<bndbox>
			<xmin>749</xmin>
			<ymin>632</ymin>
			<xmax>1885</xmax>
			<ymax>1226</ymax>
		</bndbox>
	</object>
</annotation>