<annotation>
	<folder>train2014</folder>
	<filename>IMG_4106.jpg</filename>
	<path>F:\&#22788;&#29702;&#30149;&#23475;&#25968;&#25454;&#38598;\images\train2014\IMG_4106.jpg</path>
	<source>
		<database>Unknown</database>
	</source>
	<size>
		<width>4032</width>
		<height>3024</height>
		<depth>3</depth>
	</size>
	<segmented>0</segmented>
	<object>
		<name>healthy</name>
		<pose>Unspecified</pose>
		<truncated>0</truncated>
		<difficult>0</difficult>
		<bndbox>
			<xmin>938</xmin>
			<ymin>889</ymin>
			<xmax>2109</xmax>
			<ymax>1518</ymax>
		</bndbox>
	</object>
	<object>
		<name>healthy</name>
		<pose>Unspecified</pose>
		<truncated>0</truncated>
		<difficult>0</difficult>
		<bndbox>
			<xmin>2080</xmin>
			<ymin>1282</ymin>
			<xmax>2514</xmax>
			<ymax>1547</ymax>
		</bndbox>
	</object>
	<object>
		<name>tanju_low</name>
		<pose>Unspecified</pose>
		<truncated>0</truncated>
		<difficult>0</difficult>
		<bndbox>
			<xmin>2213</xmin>
			<ymin>1249</ymin>
			<xmax>3270</xmax>
			<ymax>1696</ymax>
		</bndbox>
	</object>
	<object>
		<name>healthy</name>
		<pose>Unspecified</pose>
		<truncated>0</truncated>
		<difficult>0</difficult>
		<bndbox>
			<xmin>1219</xmin>
			<ymin>1627</ymin>
			<xmax>2164</xmax>
			<ymax>2236</ymax>
		</bndbox>
	</object>
	<object>
		<name>tanju_high</name>
		<pose>Unspecified</pose>
		<truncated>0</truncated>
		<difficult>0</difficult>
		<bndbox>
			<xmin>2153</xmin>
			<ymin>2285</ymin>
			<xmax>2438</xmax>
			<ymax>2548</ymax>
		</bndbox>
	</object>
</annotation>