<annotation>
	<folder>train</folder>
	<filename>IMG_6429.jpg</filename>
	<path>E:\dataset\images\train\IMG_6429.jpg</path>
	<source>
		<database>Unknown</database>
	</source>
	<size>
		<width>4032</width>
		<height>3024</height>
		<depth>3</depth>
	</size>
	<segmented>0</segmented>
	<object>
		<name>chihuo_high</name>
		<pose>Unspecified</pose>
		<truncated>0</truncated>
		<difficult>0</difficult>
		<bndbox>
			<xmin>1576</xmin>
			<ymin>384</ymin>
			<xmax>2529</xmax>
			<ymax>1613</ymax>
		</bndbox>
	</object>
	<object>
		<name>healthy</name>
		<pose>Unspecified</pose>
		<truncated>0</truncated>
		<difficult>0</difficult>
		<bndbox>
			<xmin>206</xmin>
			<ymin>751</ymin>
			<xmax>1398</xmax>
			<ymax>1206</ymax>
		</bndbox>
	</object>
	<object>
		<name>healthy</name>
		<pose>Unspecified</pose>
		<truncated>1</truncated>
		<difficult>0</difficult>
		<bndbox>
			<xmin>1400</xmin>
			<ymin>0</ymin>
			<xmax>2093</xmax>
			<ymax>1042</ymax>
		</bndbox>
	</object>
	<object>
		<name>chihuo_low</name>
		<pose>Unspecified</pose>
		<truncated>1</truncated>
		<difficult>0</difficult>
		<bndbox>
			<xmin>881</xmin>
			<ymin>1334</ymin>
			<xmax>1522</xmax>
			<ymax>1900</ymax>
		</bndbox>
	</object>
</annotation>