<annotation>
	<folder>train2014</folder>
	<filename>IMG_3043.jpg</filename>
	<path>F:\&#22788;&#29702;&#30149;&#23475;&#25968;&#25454;&#38598;\images\train2014\IMG_3043.jpg</path>
	<source>
		<database>Unknown</database>
	</source>
	<size>
		<width>3264</width>
		<height>2448</height>
		<depth>3</depth>
	</size>
	<segmented>0</segmented>
	<object>
		<name>healthy</name>
		<pose>Unspecified</pose>
		<truncated>1</truncated>
		<difficult>0</difficult>
		<bndbox>
			<xmin>290</xmin>
			<ymin>329</ymin>
			<xmax>657</xmax>
			<ymax>812</ymax>
		</bndbox>
	</object>
	<object>
		<name>healthy</name>
		<pose>Unspecified</pose>
		<truncated>0</truncated>
		<difficult>0</difficult>
		<bndbox>
			<xmin>812</xmin>
			<ymin>997</ymin>
			<xmax>1195</xmax>
			<ymax>1116</ymax>
		</bndbox>
	</object>
	<object>
		<name>tanju_low</name>
		<pose>Unspecified</pose>
		<truncated>0</truncated>
		<difficult>0</difficult>
		<bndbox>
			<xmin>1582</xmin>
			<ymin>1221</ymin>
			<xmax>2892</xmax>
			<ymax>1978</ymax>
		</bndbox>
	</object>
	<object>
		<name>chabing_high</name>
		<pose>Unspecified</pose>
		<truncated>0</truncated>
		<difficult>0</difficult>
		<bndbox>
			<xmin>1483</xmin>
			<ymin>1386</ymin>
			<xmax>2122</xmax>
			<ymax>1678</ymax>
		</bndbox>
	</object>
	<object>
		<name>chabing_high</name>
		<pose>Unspecified</pose>
		<truncated>0</truncated>
		<difficult>0</difficult>
		<bndbox>
			<xmin>343</xmin>
			<ymin>1233</ymin>
			<xmax>1553</xmax>
			<ymax>2170</ymax>
		</bndbox>
	</object>
	<object>
		<name>chabing_high</name>
		<pose>Unspecified</pose>
		<truncated>0</truncated>
		<difficult>0</difficult>
		<bndbox>
			<xmin>294</xmin>
			<ymin>825</ymin>
			<xmax>788</xmax>
			<ymax>1074</ymax>
		</bndbox>
	</object>
	<object>
		<name>chabing_low</name>
		<pose>Unspecified</pose>
		<truncated>0</truncated>
		<difficult>0</difficult>
		<bndbox>
			<xmin>446</xmin>
			<ymin>1025</ymin>
			<xmax>1317</xmax>
			<ymax>1417</ymax>
		</bndbox>
	</object>
</annotation>