<annotation>
	<folder>train2014</folder>
	<filename>IMG_3983.jpg</filename>
	<path>F:\&#22788;&#29702;&#30149;&#23475;&#25968;&#25454;&#38598;\images\train2014\IMG_3983.jpg</path>
	<source>
		<database>Unknown</database>
	</source>
	<size>
		<width>3264</width>
		<height>2448</height>
		<depth>3</depth>
	</size>
	<segmented>0</segmented>
	<object>
		<name>chabing_low</name>
		<pose>Unspecified</pose>
		<truncated>0</truncated>
		<difficult>0</difficult>
		<bndbox>
			<xmin>1133</xmin>
			<ymin>416</ymin>
			<xmax>1547</xmax>
			<ymax>1347</ymax>
		</bndbox>
	</object>
	<object>
		<name>chabing_low</name>
		<pose>Unspecified</pose>
		<truncated>0</truncated>
		<difficult>0</difficult>
		<bndbox>
			<xmin>1594</xmin>
			<ymin>881</ymin>
			<xmax>1955</xmax>
			<ymax>1704</ymax>
		</bndbox>
	</object>
	<object>
		<name>chabing_low</name>
		<pose>Unspecified</pose>
		<truncated>0</truncated>
		<difficult>0</difficult>
		<bndbox>
			<xmin>1579</xmin>
			<ymin>220</ymin>
			<xmax>2743</xmax>
			<ymax>904</ymax>
		</bndbox>
	</object>
</annotation>