<annotation>
	<folder>train</folder>
	<filename>IMG_3452.jpg</filename>
	<path>E:\dataset\images\train\IMG_3452.jpg</path>
	<source>
		<database>Unknown</database>
	</source>
	<size>
		<width>4032</width>
		<height>3024</height>
		<depth>3</depth>
	</size>
	<segmented>0</segmented>
	<object>
		<name>chihuo_high</name>
		<pose>Unspecified</pose>
		<truncated>0</truncated>
		<difficult>0</difficult>
		<bndbox>
			<xmin>1773</xmin>
			<ymin>1446</ymin>
			<xmax>2673</xmax>
			<ymax>2284</ymax>
		</bndbox>
	</object>
	<object>
		<name>healthy</name>
		<pose>Unspecified</pose>
		<truncated>0</truncated>
		<difficult>0</difficult>
		<bndbox>
			<xmin>324</xmin>
			<ymin>1530</ymin>
			<xmax>1766</xmax>
			<ymax>2597</ymax>
		</bndbox>
	</object>
	<object>
		<name>healthy</name>
		<pose>Unspecified</pose>
		<truncated>0</truncated>
		<difficult>0</difficult>
		<bndbox>
			<xmin>1415</xmin>
			<ymin>1740</ymin>
			<xmax>1815</xmax>
			<ymax>2059</ymax>
		</bndbox>
	</object>
	<object>
		<name>tanju_low</name>
		<pose>Unspecified</pose>
		<truncated>0</truncated>
		<difficult>0</difficult>
		<bndbox>
			<xmin>1968</xmin>
			<ymin>1777</ymin>
			<xmax>3391</xmax>
			<ymax>2774</ymax>
		</bndbox>
	</object>
	<object>
		<name>healthy</name>
		<pose>Unspecified</pose>
		<truncated>0</truncated>
		<difficult>0</difficult>
		<bndbox>
			<xmin>2075</xmin>
			<ymin>733</ymin>
			<xmax>3175</xmax>
			<ymax>1835</ymax>
		</bndbox>
	</object>
</annotation>