<annotation>
	<folder>train2014</folder>
	<filename>IMG_4580.jpg</filename>
	<path>F:\&#22788;&#29702;&#30149;&#23475;&#25968;&#25454;&#38598;\images\train2014\IMG_4580.jpg</path>
	<source>
		<database>Unknown</database>
	</source>
	<size>
		<width>4032</width>
		<height>3024</height>
		<depth>3</depth>
	</size>
	<segmented>0</segmented>
	<object>
		<name>healthy</name>
		<pose>Unspecified</pose>
		<truncated>0</truncated>
		<difficult>0</difficult>
		<bndbox>
			<xmin>1934</xmin>
			<ymin>914</ymin>
			<xmax>2396</xmax>
			<ymax>1484</ymax>
		</bndbox>
	</object>
	<object>
		<name>healthy</name>
		<pose>Unspecified</pose>
		<truncated>0</truncated>
		<difficult>0</difficult>
		<bndbox>
			<xmin>1926</xmin>
			<ymin>1623</ymin>
			<xmax>2150</xmax>
			<ymax>2247</ymax>
		</bndbox>
	</object>
	<object>
		<name>healthy</name>
		<pose>Unspecified</pose>
		<truncated>0</truncated>
		<difficult>0</difficult>
		<bndbox>
			<xmin>1714</xmin>
			<ymin>1306</ymin>
			<xmax>2059</xmax>
			<ymax>2228</ymax>
		</bndbox>
	</object>
	<object>
		<name>healthy</name>
		<pose>Unspecified</pose>
		<truncated>0</truncated>
		<difficult>0</difficult>
		<bndbox>
			<xmin>1990</xmin>
			<ymin>870</ymin>
			<xmax>3129</xmax>
			<ymax>1463</ymax>
		</bndbox>
	</object>
</annotation>