<annotation>
	<folder>train2014</folder>
	<filename>IMG_3244.jpg</filename>
	<path>F:\&#22788;&#29702;&#30149;&#23475;&#25968;&#25454;&#38598;\images\train2014\IMG_3244.jpg</path>
	<source>
		<database>Unknown</database>
	</source>
	<size>
		<width>3264</width>
		<height>2448</height>
		<depth>3</depth>
	</size>
	<segmented>0</segmented>
	<object>
		<name>chabing_low</name>
		<pose>Unspecified</pose>
		<truncated>0</truncated>
		<difficult>0</difficult>
		<bndbox>
			<xmin>448</xmin>
			<ymin>809</ymin>
			<xmax>942</xmax>
			<ymax>1336</ymax>
		</bndbox>
	</object>
	<object>
		<name>chabing_low</name>
		<pose>Unspecified</pose>
		<truncated>0</truncated>
		<difficult>0</difficult>
		<bndbox>
			<xmin>1143</xmin>
			<ymin>478</ymin>
			<xmax>1558</xmax>
			<ymax>987</ymax>
		</bndbox>
	</object>
	<object>
		<name>chabing_low</name>
		<pose>Unspecified</pose>
		<truncated>1</truncated>
		<difficult>0</difficult>
		<bndbox>
			<xmin>1208</xmin>
			<ymin>1142</ymin>
			<xmax>1719</xmax>
			<ymax>2223</ymax>
		</bndbox>
	</object>
	<object>
		<name>chabing_low</name>
		<pose>Unspecified</pose>
		<truncated>0</truncated>
		<difficult>0</difficult>
		<bndbox>
			<xmin>1913</xmin>
			<ymin>1353</ymin>
			<xmax>2442</xmax>
			<ymax>2216</ymax>
		</bndbox>
	</object>
	<object>
		<name>chabing_high</name>
		<pose>Unspecified</pose>
		<truncated>0</truncated>
		<difficult>0</difficult>
		<bndbox>
			<xmin>1731</xmin>
			<ymin>493</ymin>
			<xmax>2642</xmax>
			<ymax>1202</ymax>
		</bndbox>
	</object>
	<object>
		<name>healthy</name>
		<pose>Unspecified</pose>
		<truncated>0</truncated>
		<difficult>0</difficult>
		<bndbox>
			<xmin>946</xmin>
			<ymin>226</ymin>
			<xmax>1451</xmax>
			<ymax>762</ymax>
		</bndbox>
	</object>
</annotation>